vk2telegraph/__init__.py
vk2telegraph/__main__.py
vk2telegraph/tgph/__init__.py
vk2telegraph/tgph/backends/__init__.py
vk2telegraph/tgph/backends/bicycle_backend.py
vk2telegraph/tgph/backends/telegraph_backend.py
vk2telegraph/vk/__init__.py
vk2telegraph/vk/backends/__init__.py
vk2telegraph/vk/backends/requests_html_backend/__init__.py
vk2telegraph-0.3.dist-info/LICENSE
vk2telegraph-0.3.dist-info/METADATA
vk2telegraph-0.3.dist-info/WHEEL
vk2telegraph-0.3.dist-info/top_level.txt
vk2telegraph-0.3.dist-info/RECORD
