Metadata-Version: 2.1
Name: vk2telegraph
Version: 0.3
Summary: This script translate VK articles to Telegra.ph posts
Home-page: https://github.com/kristaller486/vk2telegraph
Author: Kristaller
Keywords: vk,telegraph,vk posts,telegra.ph
Classifier: Development Status :: 4 - Beta
Classifier: Topic :: Internet
Classifier: License :: OSI Approved :: MIT License
Classifier: Operating System :: OS Independent
Classifier: Programming Language :: Python :: 3 :: Only
Classifier: Programming Language :: Python :: 3.6
Classifier: Programming Language :: Python :: 3.7
Classifier: Programming Language :: Python :: 3.8
Classifier: Programming Language :: Python :: 3.9
Classifier: Programming Language :: Python :: 3.10
Classifier: Programming Language :: Python :: Implementation :: PyPy
License-File: LICENSE
Requires-Dist: fake-useragent
Requires-Dist: fire
Requires-Dist: telegraph
Requires-Dist: requests
Requires-Dist: beautifulsoup4
